npd_cat_corr/__init__.py
npd_cat_corr/client.py
npd_cat_corr/data_construction.py
npd_cat_corr/main.py
npd_cat_corr/reports.py
npd_category_correlation-0.2.0.dist-info/METADATA
npd_category_correlation-0.2.0.dist-info/WHEEL
npd_category_correlation-0.2.0.dist-info/entry_points.txt
npd_category_correlation-0.2.0.dist-info/top_level.txt
npd_category_correlation-0.2.0.dist-info/RECORD
