Metadata-Version: 2.1
Name: npd-category-correlation
Version: 0.2.0
Summary: Library for calculating NPD Category Correlations with Financial Data
Home-page: https://NPDGroup@dev.azure.com/NPDGroup/NPDFinancialServices/_git/NPDCategoryCorrelation
Author: Max Leonard
Author-email: maxhleonard@gmail.com
License: UNKNOWN
Platform: UNKNOWN
Classifier: Programming Language :: Python :: 3
Classifier: License :: OSI Approved :: MIT License
Classifier: Operating System :: OS Independent
Requires-Python: >=3.6
Requires-Dist: pandas
Requires-Dist: openpyxl
